djmail/__init__.py
djmail/admin.py
djmail/apps.py
djmail/core.py
djmail/exceptions.py
djmail/models.py
djmail/signals.py
djmail/tasks.py
djmail/template_mail.py
djmail/utils.py
djmail/backends/__init__.py
djmail/backends/async.py
djmail/backends/base.py
djmail/backends/celery.py
djmail/backends/default.py
djmail/management/__init__.py
djmail/management/commands/__init__.py
djmail/management/commands/djmail_delete_old_messages.py
djmail/management/commands/djmail_retry_send_messages.py
djmail/migrations/0001_initial.py
djmail/migrations/0002_auto_20161118_1347.py
djmail/migrations/__init__.py
djmail-2.0.0.dist-info/AUTHORS.md
djmail-2.0.0.dist-info/LICENSE
djmail-2.0.0.dist-info/METADATA
djmail-2.0.0.dist-info/WHEEL
djmail-2.0.0.dist-info/top_level.txt
djmail-2.0.0.dist-info/RECORD
